setup.py
postmarkup/__init__.py
postmarkup/parser.py
postmarkup/tests.py
postmarkup.egg-info/PKG-INFO
postmarkup.egg-info/SOURCES.txt
postmarkup.egg-info/dependency_links.txt
postmarkup.egg-info/requires.txt
postmarkup.egg-info/top_level.txt