Metadata-Version: 1.1
Name: postmarkup
Version: 1.2.1
Summary: BBCode to (X)HTML rendering engine
Home-page: http://code.google.com/p/postmarkup/
Author: Will McGugan
Author-email: will@willmcgugan.com
License: Python Software Foundation License
Download-URL: http://code.google.com/p/postmarkup/downloads/list
Platform: any
Classifier: Development Status :: 5 - Production/Stable
Classifier: Intended Audience :: Developers
Classifier: Programming Language :: Python
Classifier: Programming Language :: Python :: 2.5
Classifier: Programming Language :: Python :: 2.6
Classifier: Programming Language :: Python :: 2.7
Classifier: Programming Language :: Python :: 3
Classifier: License :: OSI Approved :: Python Software Foundation License
Classifier: Operating System :: OS Independent
Classifier: Topic :: Text Processing :: Markup
